mongo_s3_archiver/__init__.py
mongo_s3_archiver/__main__.py
mongo_s3_archiver/dump.py
mongo_s3_archiver/helpers.py
mongo_s3_archiver/notifications.py
mongo_s3_archiver/s3.py
mongo_s3_archiver-0.1.2.dist-info/licenses/LICENSE
mongo_s3_archiver-0.1.2.dist-info/METADATA
mongo_s3_archiver-0.1.2.dist-info/WHEEL
mongo_s3_archiver-0.1.2.dist-info/entry_points.txt
mongo_s3_archiver-0.1.2.dist-info/top_level.txt
mongo_s3_archiver-0.1.2.dist-info/RECORD
