Metadata-Version: 2.4
Name: mongo-s3-archiver
Version: 0.1.2
Summary: Backup utility for MongoDB. Compatible with Azure, Amazon Web Services and Google Cloud Platform.
Home-page: https://github.com/hadikoub/mongo-s3-archiver
Author: Vladislav I. Kulbatski 
Author-email: hi@exesse.org
Maintainer: Hadi Koubeissy
Maintainer-email: 123.hadikoubeissy@gmail.com
License: MIT
Project-URL: Source, https://github.com/hadikoub/mongo-s3-archiver
Project-URL: Upstream Project, https://github.com/exesse/mongodump-s3
Classifier: License :: OSI Approved :: MIT License
Classifier: Programming Language :: Python :: 3
Classifier: Programming Language :: Python :: 3.8
License-File: LICENSE
Requires-Dist: requests>=2.26.0
Requires-Dist: hurry.filesize==0.9
Requires-Dist: python-dotenv>=0.18.0
Requires-Dist: azure-storage-blob>=12.8.1
Requires-Dist: boto3>=1.17.111
Requires-Dist: google-cloud-storage>=1.41.0
Requires-Dist: pymongo>=4.0.0
Dynamic: author
Dynamic: author-email
Dynamic: classifier
Dynamic: description
Dynamic: description-content-type
Dynamic: home-page
Dynamic: license
Dynamic: license-file
Dynamic: maintainer
Dynamic: maintainer-email
Dynamic: project-url
Dynamic: requires-dist
Dynamic: summary
